CONTRIBUTING.md
LICENSE
MANIFEST.in
Makefile
README.md
make.bat
requirements-dev.txt
requirements-test.txt
requirements.txt
setup.py
src/mars_profiling/__init__.py
src/mars_profiling/config.py
src/mars_profiling/config_default.yaml
src/mars_profiling/config_minimal.yaml
src/mars_profiling/profile_report.py
src/mars_profiling/serialize_report.py
src/mars_profiling/version.py
src/mars_profiling.egg-info/PKG-INFO
src/mars_profiling.egg-info/SOURCES.txt
src/mars_profiling.egg-info/dependency_links.txt
src/mars_profiling.egg-info/entry_points.txt
src/mars_profiling.egg-info/requires.txt
src/mars_profiling.egg-info/top_level.txt
src/mars_profiling/controller/__init__.py
src/mars_profiling/controller/console.py
src/mars_profiling/controller/pandas_decorator.py
src/mars_profiling/model/__init__.py
src/mars_profiling/model/base.py
src/mars_profiling/model/correlations.py
src/mars_profiling/model/describe.py
src/mars_profiling/model/messages.py
src/mars_profiling/model/sample.py
src/mars_profiling/model/summary.py
src/mars_profiling/report/__init__.py
src/mars_profiling/report/formatters.py
src/mars_profiling/report/presentation/__init__.py
src/mars_profiling/report/presentation/frequency_table_utils.py
src/mars_profiling/report/presentation/core/__init__.py
src/mars_profiling/report/presentation/core/collapse.py
src/mars_profiling/report/presentation/core/container.py
src/mars_profiling/report/presentation/core/duplicate.py
src/mars_profiling/report/presentation/core/frequency_table.py
src/mars_profiling/report/presentation/core/frequency_table_small.py
src/mars_profiling/report/presentation/core/html.py
src/mars_profiling/report/presentation/core/image.py
src/mars_profiling/report/presentation/core/item_renderer.py
src/mars_profiling/report/presentation/core/renderable.py
src/mars_profiling/report/presentation/core/root.py
src/mars_profiling/report/presentation/core/sample.py
src/mars_profiling/report/presentation/core/table.py
src/mars_profiling/report/presentation/core/toggle_button.py
src/mars_profiling/report/presentation/core/variable.py
src/mars_profiling/report/presentation/core/variable_info.py
src/mars_profiling/report/presentation/core/warnings.py
src/mars_profiling/report/presentation/flavours/__init__.py
